LICENSE
pysigtool.py
pysigtool-0.1.4.dist-info/entry_points.txt
pysigtool-0.1.4.dist-info/LICENSE
pysigtool-0.1.4.dist-info/WHEEL
pysigtool-0.1.4.dist-info/METADATA
pysigtool-0.1.4.dist-info/RECORD
