Metadata-Version: 2.1
Name: pysigtool
Version: 0.1.4
Summary: Extract digital signatures contained in a PE file.
Home-page: https://github.com/kohnakagawa/pysigtool
License: Apache-2.0
Author: Koh M. Nakagawa
Author-email: tsunekou1019@gmail.com
Requires-Python: >=3.6,<4.0
Classifier: License :: OSI Approved :: Apache Software License
Classifier: Programming Language :: Python :: 3
Classifier: Programming Language :: Python :: 3.6
Classifier: Programming Language :: Python :: 3.7
Classifier: Programming Language :: Python :: 3.8
Requires-Dist: lief (>=0.10.1,<0.11.0)
Project-URL: Repository, https://github.com/kohnakagawa/pysigtool
